IN_utility/__init__.py
IN_utility/script.py
IN_Utility-1.0.1.dist-info/LICENSE
IN_Utility-1.0.1.dist-info/METADATA
IN_Utility-1.0.1.dist-info/WHEEL
IN_Utility-1.0.1.dist-info/entry_points.txt
IN_Utility-1.0.1.dist-info/top_level.txt
IN_Utility-1.0.1.dist-info/RECORD
