Metadata-Version: 2.1
Name: IN-Utility
Version: 1.0.1
Summary: A utility for text manipulation, compression, and task management.
Home-page: https://github.com/SinghSuraj-04092002/IN_Utility.git
Author: Suraj Singh
Author-email: surajsingh04092002@gmail.com
License: UNKNOWN
Platform: UNKNOWN
Classifier: Programming Language :: Python :: 3
Classifier: License :: OSI Approved :: MIT License
Classifier: Operating System :: OS Independent
License-File: LICENSE
